{
  "project_info": {
    "project_number": "107253056603",
    "project_id": "chat-app-d5725",
    "storage_bucket": "chat-app-d5725.appspot.com"
  },
  "client": [
    {
      "client_info": {
        "mobilesdk_app_id": "1:107253056603:android:76a6d55b2c509062006b7e",
        "android_client_info": {
          "package_name": "com.example.chat"
        }
      },
      "oauth_client": [
        {
          "client_id": "107253056603-r5m6t7n3a26sctllg5krff3b2s873f40.apps.googleusercontent.com",
          "client_type": 3
        }
      ],
      "api_key": [
        {
          "current_key": "AIzaSyDDN8n_akxoPGUndSNAd5LO2fXKM-Ql3yg"
        }
      ],
      "services": {
        "appinvite_service": {
          "other_platform_oauth_client": [
            {
              "client_id": "107253056603-r5m6t7n3a26sctllg5krff3b2s873f40.apps.googleusercontent.com",
              "client_type": 3
            }
          ]
        }
      }
    }
  ],
  "configuration_version": "1"
}